{
 "runId": "run-2026-07-16T02-30-34",
 "mode": "live",
 "startedAt": "2026-07-16T02:30:34.001Z",
 "films": 6,
 "published": [],
 "held": [],
 "rejected": [],
 "skipped": [
  {
   "tag": "enola-holmes-3-netflix-top10Ă—NETFLIX-TOP10",
   "reason": "parked dead"
  },
  {
   "tag": "the-doorman-netflix-top10Ă—NETFLIX-TOP10",
   "reason": "parked dead"
  },
  {
   "tag": "little-brother-netflix-top10Ă—NETFLIX-TOP10",
   "reason": "parked dead"
  },
  {
   "tag": "rust-creek-netflix-top10Ă—NETFLIX-TOP10",
   "reason": "parked dead"
  },
  {
   "tag": "old-henry-netflix-top10Ă—NETFLIX-TOP10",
   "reason": "parked dead"
  },
  {
   "tag": "the-boss-baby-netflix-top10Ă—NETFLIX-TOP10",
   "reason": "parked dead"
  }
 ],
 "blocked": [],
 "finishedAt": "2026-07-16T02:30:41.161Z",
 "meter": {
  "byRole": {
   "gatherer": {
    "calls": 1,
    "errors": 0,
    "in": 2945,
    "out": 1798,
    "usd": 0.00101,
    "ms": 3658
   },
   "finder": {
    "calls": 1,
    "errors": 0,
    "in": 3252,
    "out": 640,
    "usd": 0.0002,
    "ms": 2294
   }
  },
  "totalUsd": 0.00122
 },
 "openrouterTotalUsd": 0.00122
}