{
  "id": "music-profile-bad-bunny-career",
  "slug": "bad-bunny-the-career-that-rewired-pop",
  "status": "published",
  "stages": {
    "attempt1": {
      "score": 88,
      "cat": "music/profiles-artists",
      "img": "/images/articles/bad-bunny-the-career-that-rewired-pop.jpg",
      "hardBlocks": [],
      "badClaims": 0
    }
  },
  "scorecard": {
    "score": 88,
    "subscores": {
      "accuracy": 10,
      "readability": 9,
      "humanVoice": 9,
      "phrasing": 9,
      "curiosity": 9,
      "structure": 9,
      "infoGain": 9,
      "seo": 8,
      "faqQuality": 8,
      "completeness": 9
    },
    "strengths": [
      "Strong reader-first approach prioritizing narrative flow and engagement.",
      "Excellent use of subheads to break up text and guide the reader.",
      "Clear and concise lead that answers the core question quickly.",
      "Human voice is evident, with specific examples and a clear point of view.",
      "Accurate sourcing and adherence to provided facts.",
      "Good information gain through analysis rather than just summary.",
      "Well-structured article with a logical progression of ideas.",
      "FAQ section provides genuinely useful, supplementary information.",
      "Career arc section is a valuable visual aid."
    ],
    "weaknesses": [
      "SEO score is slightly lower due to the emphasis on reader experience over keyword stuffing, which is a deliberate choice but noted.",
      "FAQ quality could be slightly improved by ensuring all answers are as concise as the questions.",
      "While generally fluent, a few transitions could be smoother."
    ],
    "deterministic": {
      "words": 476,
      "h2s": 5,
      "h2Questions": 4,
      "internalLinks": 0,
      "externalLinks": 3,
      "hasSources": true,
      "faqCount": 4,
      "ktCount": 5,
      "kwInTitle": true,
      "kwInFirst100": true,
      "kwInH2": false,
      "maxSentence": 50,
      "avgSentence": 18,
      "flesch": 55,
      "bannedTells": 0,
      "fillerPraise": 0,
      "kwExact": 0,
      "hardBlocks": []
    },
    "hardBlocks": []
  },
  "score": 88,
  "category": "music",
  "subcategory": "profiles-artists",
  "audit": {
    "ok": true,
    "internalLinks": 0,
    "failed": []
  },
  "ms": 148451
}