{
  "slug": "mark-hamill-s-star-wars-lightsaber-smashes-predictions-sells-for-record-sum",
  "assets": [
    {
      "entity": "Mark Hamill",
      "url": "https://image.tmdb.org/t/p/original/zMQ93JTLW8KxusKhOlHFZhih3YQ.jpg",
      "prov": "tmdb-profile"
    },
    {
      "entity": "Mark Hamill",
      "url": "https://image.tmdb.org/t/p/original/2ZulC2Ccq1yv3pemusks6Zlfy2s.jpg",
      "prov": "tmdb-profile"
    },
    {
      "entity": "Mark Hamill",
      "url": "https://image.tmdb.org/t/p/original/bMonrxrIEpokFTXUbZx8VnZ7xb3.jpg",
      "prov": "tmdb-profile"
    },
    {
      "entity": "Mark Hamill",
      "url": "https://upload.wikimedia.org/wikipedia/commons/d/dc/Mark_Hamill_by_Gage_Skidmore_4.jpg",
      "prov": "wikipedia"
    },
    {
      "entity": "Heritage Auctions",
      "url": "https://nypost.com/wp-content/uploads/sites/2/2026/07/134590931.jpg?quality=75&amp;strip=all&amp;w=1024",
      "prov": "news:nypost.com"
    },
    {
      "entity": "Heritage Auctions",
      "url": "https://nypost.com/wp-content/uploads/sites/2/2026/07/134590931.jpg?quality=75&#038;strip=all&#038;w=1200",
      "prov": "news:nypost.com"
    },
    {
      "entity": "Heritage Auctions",
      "url": "https://heise.cloudimg.io/bound/1200x1200/q85.png-lossy-85.webp-lossy-85.foil1/_www-heise-de_/imgs/18/5/1/1/8/2/2/7/videoframe_65191-da83e5238088b8a7.png",
      "prov": "news:heise.de"
    },
    {
      "entity": "Star Wars: Episode V – The Empire Strikes Back",
      "url": "https://nypost.com/wp-content/uploads/sites/2/2026/07/134590931.jpg?quality=75&amp;strip=all&amp;w=1024",
      "prov": "topup-news"
    },
    {
      "entity": "Star Wars: Episode V – The Empire Strikes Back",
      "url": "https://nypost.com/wp-content/uploads/sites/2/2026/07/134590931.jpg?quality=75&#038;strip=all&#038;w=1200",
      "prov": "topup-news"
    },
    {
      "entity": "Star Wars: Episode V – The Empire Strikes Back",
      "url": "https://image.tmdb.org/t/p/original/k9pshruhCpJAdH9RaGJO6jaWQ4X.jpg",
      "prov": "tmdb-backdrop"
    },
    {
      "entity": "Star Wars: Episode V – The Empire Strikes Back",
      "url": "https://image.tmdb.org/t/p/original/b37U5gN6itEjaFcmaKhUOqG2Mkt.jpg",
      "prov": "tmdb-backdrop"
    },
    {
      "entity": "Heritage's Hollywood & Entertainment Signature Auction",
      "url": "https://s.yimg.com/lo/mysterio/api/1c9abd329553bb3d45eddec227faf98569910b8cfce4f923cd18ae49936847c9/lightyear_networkapi/resizefill_w1000_h600;quality_80;format_webp/https:%2F%2Fmedia.zenfs.com%2Fen%2Ftalker_news_345%2F131e2a4fb1b64a835dccde4c534f1fb3",
      "prov": "news:yahoo.com"
    },
    {
      "entity": "Heritage's Hollywood & Entertainment Signature Auction",
      "url": "https://nypost.com/wp-content/uploads/sites/2/2026/07/134590931.jpg?quality=75&amp;strip=all&amp;w=1024",
      "prov": "news:nypost.com"
    },
    {
      "entity": "Heritage's Hollywood & Entertainment Signature Auction",
      "url": "https://nypost.com/wp-content/uploads/sites/2/2026/07/134590931.jpg?quality=75&#038;strip=all&#038;w=1200",
      "prov": "news:nypost.com"
    },
    {
      "entity": "Heritage's Hollywood & Entertainment Signature Auction",
      "url": "https://assets1.cbsnewsstatic.com/hub/i/r/2026/06/16/c7b4de6c-f418-4558-9dca-93ce57964576/thumbnail/1200x630/b2402c90f6d607640bdd2e601e1959c0/ap26166704650758.jpg",
      "prov": "news:cbsnews.com"
    }
  ],
  "at": "2026-07-16T16:48:00.971Z"
}